fetch_ready_issues.py
hooks.py
ralph.py
agents/__init__.py
agents/base.py
agents/claude.py
agents/copilot.py
pyralph-0.1.0.dist-info/licenses/LICENSE
pyralph-0.1.0.dist-info/METADATA
pyralph-0.1.0.dist-info/WHEEL
pyralph-0.1.0.dist-info/entry_points.txt
pyralph-0.1.0.dist-info/top_level.txt
pyralph-0.1.0.dist-info/RECORD
