Metadata-Version: 2.4
Name: pyralph
Version: 0.1.0
Summary: Autonomous software development agent that iteratively builds projects
Author: Ralph Agent
License: MIT License
Project-URL: Homepage, https://github.com/pavalso/pyralph
Project-URL: Repository, https://github.com/pavalso/pyralph
Project-URL: Documentation, https://github.com/pavalso/pyralph#readme
Keywords: ai,agent,automation,cli,development,llm
Classifier: Development Status :: 3 - Alpha
Classifier: License :: OSI Approved :: MIT License
Classifier: Programming Language :: Python :: 3
Classifier: Programming Language :: Python :: 3.8
Classifier: Programming Language :: Python :: 3.9
Classifier: Programming Language :: Python :: 3.10
Classifier: Programming Language :: Python :: 3.11
Classifier: Programming Language :: Python :: 3.12
Classifier: Operating System :: OS Independent
Classifier: Intended Audience :: Developers
Requires-Python: >=3.8
License-File: LICENSE
Requires-Dist: pyyaml>=6.0
Dynamic: license-file
